rmoptions/__init__.py
rmoptions/rm_option.py
rmoptions/rm_option_handler.py
rmoptions/mapper/__init__.py
rmoptions/mapper/base_mapper.py
rmoptions/mapper/float_mapper.py
rmoptions/mapper/int_mapper.py
rm_options-2.0.1.dist-info/LICENSE
rm_options-2.0.1.dist-info/METADATA
rm_options-2.0.1.dist-info/WHEEL
rm_options-2.0.1.dist-info/entry_points.txt
rm_options-2.0.1.dist-info/top_level.txt
rm_options-2.0.1.dist-info/RECORD
